README.md
setup.py
simple_ts.egg-info/PKG-INFO
simple_ts.egg-info/SOURCES.txt
simple_ts.egg-info/dependency_links.txt
simple_ts.egg-info/requires.txt
simple_ts.egg-info/top_level.txt
simplets/__init__.py
simplets/simplets.py