Metadata-Version: 2.1
Name: simple-ts
Version: 0.9.1
Summary: A simple time series analysis package
Author: Alisson Louly
